AUTHORS
CHANGELOG.rst
CONTRIBUTING.rst
LICENSE
README.rst
machina/__init__.py
machina/apps/__init__.py
machina/apps/forum/__init__.py
machina/apps/forum/abstract_models.py
machina/apps/forum/admin.py
machina/apps/forum/apps.py
machina/apps/forum/forms.py
machina/apps/forum/migrations/0001_initial.py
machina/apps/forum/migrations/0002_auto_20150725_0512.py
machina/apps/forum/migrations/0003_remove_forum_is_active.py
machina/apps/forum/migrations/0004_auto_20170504_2108.py
machina/apps/forum/migrations/0005_auto_20170504_2113.py
machina/apps/forum/migrations/0006_auto_20170523_2036.py
machina/apps/forum/migrations/0007_auto_20170523_2140.py
machina/apps/forum/migrations/0008_forum_last_post.py
machina/apps/forum/migrations/0009_auto_20170928_2327.py
machina/apps/forum/migrations/0010_auto_20181103_1401.py
machina/apps/forum/migrations/0011_auto_20190627_2132.py
machina/apps/forum/migrations/__init__.py
machina/apps/forum/models.py
machina/apps/forum/receivers.py
machina/apps/forum/signals.py
machina/apps/forum/urls.py
machina/apps/forum/views.py
machina/apps/forum/visibility.py
machina/apps/forum_conversation/__init__.py
machina/apps/forum_conversation/abstract_models.py
machina/apps/forum_conversation/admin.py
machina/apps/forum_conversation/apps.py
machina/apps/forum_conversation/forms.py
machina/apps/forum_conversation/forum_attachments/__init__.py
machina/apps/forum_conversation/forum_attachments/abstract_models.py
machina/apps/forum_conversation/forum_attachments/admin.py
machina/apps/forum_conversation/forum_attachments/apps.py
machina/apps/forum_conversation/forum_attachments/cache.py
machina/apps/forum_conversation/forum_attachments/forms.py
machina/apps/forum_conversation/forum_attachments/migrations/0001_initial.py
machina/apps/forum_conversation/forum_attachments/migrations/0002_auto_20181103_1404.py
machina/apps/forum_conversation/forum_attachments/migrations/__init__.py
machina/apps/forum_conversation/forum_attachments/models.py
django_machina-1.3.1.dist-info/LICENSE
django_machina-1.3.1.dist-info/METADATA
django_machina-1.3.1.dist-info/WHEEL
django_machina-1.3.1.dist-info/RECORD
