Metadata-Version: 2.1
Name: django-machina
Version: 1.3.1
Summary: A Django forum engine for building powerful community driven websites.
Home-page: https://github.com/ellmetha/django-machina
License: BSD-3-Clause
Keywords: django,forum,board,messages
Author: Morgan Aubert
Author-email: me@morganaubert.name
Requires-Python: >=3.6,<4.0
Classifier: Development Status :: 4 - Beta
Classifier: Environment :: Web Environment
Classifier: Framework :: Django
Classifier: Intended Audience :: Developers
Classifier: License :: OSI Approved :: BSD License
Classifier: Natural Language :: English
Classifier: Programming Language :: Python
Classifier: Programming Language :: Python :: 3
Classifier: Programming Language :: Python :: 3.6
Classifier: Programming Language :: Python :: 3.7
Classifier: Programming Language :: Python :: 3.8
Classifier: Programming Language :: Python :: 3.9
Classifier: Programming Language :: Python :: 3.10
Classifier: Programming Language :: Python :: 3.11
Classifier: Topic :: Internet :: WWW/HTTP :: Dynamic Content :: Message Boards
Requires-Dist: django (>=3.2)
Requires-Dist: django-haystack (>=2.1)
Requires-Dist: django-mptt (>=0.10.0)
Requires-Dist: django-widget-tweaks (>=1.4)
Requires-Dist: markdown2 (>=2.3)
Requires-Dist: pillow (>=2.2)
Project-URL: Repository, https://github.com/ellmetha/django-machina
